forismatic/__init__.py
forismatic/forismatic.py
forismatic-0.1.3.dist-info/LICENSE.txt
forismatic-0.1.3.dist-info/METADATA
forismatic-0.1.3.dist-info/WHEEL
forismatic-0.1.3.dist-info/top_level.txt
forismatic-0.1.3.dist-info/RECORD
