Metadata-Version: 2.1
Name: forismatic
Version: 0.1.3
Summary: An unofficial API wrapper for the forismatic.com API.
Home-page: https://github.com/ihumanbeing/forismatic.py
Author: Adam Baird
Author-email: adamjohnbaird321@gmail.com
License: MIT
Download-URL: https://pypi.org/project/forismatic.py/
Keywords: Forismatic,ForismaticPy,Forismatic.py
Platform: UNKNOWN
Classifier: License :: OSI Approved :: MIT License
Classifier: Operating System :: OS Independent
Classifier: Programming Language :: Python :: 3.6
Classifier: Programming Language :: Python :: 3.7
Classifier: Programming Language :: Python :: 3.8
Requires-Python: >=3.6
